{
    "data": [
      {
        "report-name": "Lorem Ipsum6092",
        "condenser-name": "PB1237",
        "time-frame": "04/25/2020 to 07/25/2020",
        "time-stamp": 1596711974,
        "created-by": "Vincent"
      },
      {
        "report-name": "Lorem Ipsum6092",
        "condenser-name": "PB1232",
        "time-frame": "03/25/2020 to 03/25/2020",
        "time-stamp": 1596711974,
        "created-by": "Vincent"
      },
      {
        "report-name": "Lorem Ipsum6092",
        "condenser-name": "PB4747",
        "time-frame": "04/22/2020 to 07/22/2020",
        "time-stamp": 1596711974,
        "created-by": "Vincent"
      },
      {
        "report-name": "Lorem Ipsum6092",
        "condenser-name": "PB1234",
        "time-frame": "04/25/2020 to 07/25/2020",
        "time-stamp": 1596711974,
        "created-by": "Vincent"
      },
      {
        "report-name": "Lorem Ipsum6092",
        "condenser-name": "PB4556",
        "time-frame": "04/25/2020 to 07/25/2020",
        "time-stamp": 1596711974,
        "created-by": "Vincent"
      },
      {
        "report-name": "Lorem Ipsum6092",
        "condenser-name": "PB3243",
        "time-frame": "04/25/2020 to 07/25/2020",
        "time-stamp": 1596711974,
        "created-by": "Vincent"
      },
      {
        "report-name": "Lorem Ipsum6092",
        "condenser-name": "PB2344",
        "time-frame": "04/25/2020 to 07/25/2020",
        "time-stamp": 1596711974,
        "created-by": "Vincent"
      },
      {
        "report-name": "Lorem Ipsum1234",
        "condenser-name": "PB6363",
        "time-frame": "04/25/2020 to 07/25/2020",
        "time-stamp": 1596711974,
        "created-by": "Vincent"
      },
      {
        "report-name": "Lorem Ipsum1234",
        "condenser-name": "PB8474",
        "time-frame": "04/25/2020 to 07/25/2020",
        "time-stamp": 1596711974,
        "created-by": "Francis"
      },
      {
        "report-name": "Lorem Ipsum8989",
        "condenser-name": "PB8484",
        "time-frame": "04/25/2020 to 07/25/2020",
        "time-stamp": 1596711974,
        "created-by": "Francis"
      },
      {
        "report-name": "Lorem Ipsum9098",
        "condenser-name": "PB7447",
        "time-frame": "04/25/2020 to 07/25/2020",
        "time-stamp": 1596711974,
        "created-by": "Francis"
      },
      {
        "report-name": "15967119746232",
        "condenser-name": "PB4749",
        "time-frame": "04/25/2020 to 07/25/2020",
        "time-stamp": 1596711974,
        "created-by": "Francis"
      },
      {
        "report-name": "Lorem Ipsum7889",
        "condenser-name": "PB9474",
        "time-frame": "04/25/2020 to 07/25/2020",
        "time-stamp": 1596711974,
        "created-by": "Carlos"
      },
      {
        "report-name": "Lorem Ipsum7854",
        "condenser-name": "PB4747",
        "time-frame": "04/25/2020 to 07/25/2020",
        "time-stamp": 1596711974,
        "created-by": "Carlos"
      }
     
    ]
  }
  